{
  "/blog/archive-447": {
    "__comp": "9e4087bc",
    "__context": {
      "plugin": "7dc665dd"
    },
    "archive": "b2f554cd"
  },
  "/blog/change-ssh-port-in-linux-centos-660": {
    "__comp": "ccc49370",
    "__context": {
      "plugin": "7dc665dd"
    },
    "sidebar": "814f3328",
    "content": "4912db49"
  },
  "/blog/index-dsjfs-db6": {
    "__comp": "1bd0a467",
    "__context": {
      "plugin": "9cf27df4"
    },
    "config": "5e9f5e1a"
  },
  "/blog/markdown-page-e34": {
    "__comp": "1f391b9e",
    "__context": {
      "plugin": "9cf27df4"
    },
    "content": "393be207"
  },
  "/blog/tags-c33": {
    "__comp": "01a85c17",
    "__context": {
      "plugin": "7dc665dd"
    },
    "sidebar": "814f3328",
    "tags": "a7023ddc"
  },
  "/blog/tags/firewalld-0f6": {
    "__comp": "6875c492",
    "__context": {
      "plugin": "7dc665dd"
    },
    "sidebar": "814f3328",
    "items": [
      {
        "content": "e0995246"
      }
    ],
    "tag": "27c5df5f",
    "listMetadata": "948ecb50"
  },
  "/blog/tags/linux-1fa": {
    "__comp": "6875c492",
    "__context": {
      "plugin": "7dc665dd"
    },
    "sidebar": "814f3328",
    "items": [
      {
        "content": "e0995246"
      }
    ],
    "tag": "dd5bc5cd",
    "listMetadata": "70c84758"
  },
  "/blog/tags/semanage-4de": {
    "__comp": "6875c492",
    "__context": {
      "plugin": "7dc665dd"
    },
    "sidebar": "814f3328",
    "items": [
      {
        "content": "e0995246"
      }
    ],
    "tag": "6a3ff6f9",
    "listMetadata": "b9cd51c7"
  },
  "/blog/tags/ssh-0f5": {
    "__comp": "6875c492",
    "__context": {
      "plugin": "7dc665dd"
    },
    "sidebar": "814f3328",
    "items": [
      {
        "content": "e0995246"
      }
    ],
    "tag": "f78117e4",
    "listMetadata": "d760667c"
  },
  "/blog/docs-f1b": {
    "__comp": "1be78505",
    "__context": {
      "plugin": "218d7dde"
    },
    "versionMetadata": "935f2afb"
  },
  "/blog/docs/category/tutorial---basics-ca7": {
    "__comp": "14eb3368",
    "categoryGeneratedIndex": "d2ff9370"
  },
  "/blog/docs/category/tutorial---extras-e03": {
    "__comp": "14eb3368",
    "categoryGeneratedIndex": "bd5b347c"
  },
  "/blog/docs/intro-7c7": {
    "__comp": "17896441",
    "content": "0e384e19"
  },
  "/blog/docs/tutorial-basics/congratulations-ec4": {
    "__comp": "17896441",
    "content": "822bd8ab"
  },
  "/blog/docs/tutorial-basics/create-a-blog-post-7b5": {
    "__comp": "17896441",
    "content": "533a09ca"
  },
  "/blog/docs/tutorial-basics/create-a-document-d31": {
    "__comp": "17896441",
    "content": "1e4232ab"
  },
  "/blog/docs/tutorial-basics/create-a-page-6f2": {
    "__comp": "17896441",
    "content": "5c868d36"
  },
  "/blog/docs/tutorial-basics/deploy-your-site-cbf": {
    "__comp": "17896441",
    "content": "f55d3e7a"
  },
  "/blog/docs/tutorial-basics/markdown-features-b11": {
    "__comp": "17896441",
    "content": "18c41134"
  },
  "/blog/docs/tutorial-extras/manage-docs-versions-485": {
    "__comp": "17896441",
    "content": "dff1c289"
  },
  "/blog/docs/tutorial-extras/translate-your-site-031": {
    "__comp": "17896441",
    "content": "e44a2883"
  },
  "/blog/-6eb": {
    "__comp": "a6aa9e1f",
    "__context": {
      "plugin": "7dc665dd"
    },
    "sidebar": "814f3328",
    "items": [
      {
        "content": "e0995246"
      }
    ],
    "metadata": "44176adc"
  }
}